oodi/__init__.py
oodi/cli.py
oodi/configuration.py
oodi/constants.py
oodi/version.py
oodi/bin/__init__.py
oodi/bin/oodi.py
oodi/bin/commands/__init__.py
oodi/bin/commands/albumart.py
oodi/bin/commands/base.py
oodi/bin/commands/codecs.py
oodi/bin/commands/libraries.py
oodi/bin/commands/metadata.py
oodi/bin/commands/tags.py
oodi/codecs/__init__.py
oodi/codecs/base.py
oodi/codecs/configuration.py
oodi/codecs/constants.py
oodi/codecs/utils.py
oodi/codecs/aac/__init__.py
oodi/codecs/aac/audiofile.py
oodi/codecs/aac/decoder.py
oodi/codecs/aac/encoder.py
oodi/codecs/aac/tagparser.py
oodi/codecs/aif/__init__.py
oodi/codecs/aif/audiofile.py
oodi/codecs/aif/constants.py
oodi/codecs/aif/decoder.py
oodi/codecs/aif/encoder.py
oodi/codecs/aif/tagparser.py
oodi/codecs/alac/__init__.py
oodi/codecs/alac/audiofile.py
oodi/codecs/alac/decoder.py
oodi/codecs/alac/encoder.py
oodi/codecs/alac/tagparser.py
oodi/codecs/caf/__init__.py
oodi/codecs/caf/audiofile.py
oodi/codecs/caf/decoder.py
oodi/codecs/caf/encoder.py
oodi/codecs/flac/__init__.py
oodi/codecs/flac/audiofile.py
oodi/codecs/flac/decoder.py
oodi/codecs/flac/encoder.py
oodi/codecs/flac/tagparser.py
oodi/codecs/mp3/__init__.py
oodi/codecs/mp3/audiofile.py
oodi/codecs/mp3/constants.py
oodi/codecs/mp3/decoder.py
oodi/codecs/mp3/encoder.py
oodi/codecs/mp3/tagparser.py
oodi/codecs/mp4/__init__.py
oodi/codecs/mp4/audiofile.py
oodi/codecs/mp4/constants.py
oodi/codecs/mp4/tagparser.py
oodi/codecs/ogg/__init__.py
oodi/codecs/ogg/constants.py
oodi/codecs/ogg/tagparser.py
oodi/codecs/opus/__init__.py
oodi/codecs/opus/audiofile.py
oodi/codecs/opus/decoder.py
oodi/codecs/opus/encoder.py
oodi/codecs/opus/tagparser.py
oodi/codecs/vorbis/__init__.py
oodi/codecs/vorbis/audiofile.py
oodi/codecs/vorbis/decoder.py
oodi/codecs/vorbis/encoder.py
oodi/codecs/vorbis/tagparser.py
oodi/codecs/wav/__init__.py
oodi/codecs/wav/audiofile.py
oodi/codecs/wav/decoder.py
oodi/codecs/wav/encoder.py
oodi/codecs/wavpack/__init__.py
oodi/codecs/wavpack/audiofile.py
oodi-1.0.dist-info/METADATA
oodi-1.0.dist-info/WHEEL
oodi-1.0.dist-info/entry_points.txt
oodi-1.0.dist-info/top_level.txt
oodi-1.0.dist-info/RECORD
